unpaddedbase64.py
unpaddedbase64-2.0.0.dist-info/LICENSE
unpaddedbase64-2.0.0.dist-info/WHEEL
unpaddedbase64-2.0.0.dist-info/METADATA
unpaddedbase64-2.0.0.dist-info/RECORD
