Metadata-Version: 2.1
Name: unpaddedbase64
Version: 2.0.0
Summary: Encode and decode Base64 without "=" padding
Home-page: https://github.com/matrix-org/python-unpaddedbase64
License: Apache-2.0
Keywords: base64
Author: The Matrix.org Foundation C.I.C.
Requires-Python: >=3.6,<4.0
Classifier: License :: OSI Approved :: Apache Software License
Classifier: Programming Language :: Python :: 3
Classifier: Programming Language :: Python :: 3.6
Classifier: Programming Language :: Python :: 3.7
Classifier: Programming Language :: Python :: 3.8
Classifier: Programming Language :: Python :: 3.9
Project-URL: Issue Tracker, https://github.com/matrix-org/python-unpaddedbase64/issues
